lightseq/liblightseq_op.so
lightseq/__init__.py
lightseq_tf2.4.1_cuda11.0.221-2.0.4.dist-info/top_level.txt
lightseq_tf2.4.1_cuda11.0.221-2.0.4.dist-info/RECORD
lightseq_tf2.4.1_cuda11.0.221-2.0.4.dist-info/WHEEL
lightseq_tf2.4.1_cuda11.0.221-2.0.4.dist-info/METADATA
lightseq_tf2.4.1_cuda11.0.221.libs/libcudart-3f3c6934.so.11.0.221
